harbor_ls/__init__.py
harbor_ls/__main__.py
harbor_ls-1.0.3.dist-info/licenses/LICENSE
harbor_ls-1.0.3.dist-info/METADATA
harbor_ls-1.0.3.dist-info/WHEEL
harbor_ls-1.0.3.dist-info/top_level.txt
harbor_ls-1.0.3.dist-info/RECORD
