Metadata-Version: 2.4
Name: harbor_ls
Version: 1.0.3
Summary: Simple cli to scan Harbor project/repo/artefact API
Author-email: nipil <nipil@users.noreply.github.com>
License-Expression: MIT
Project-URL: Homepage, https://github.com/nipil/harbor-ls
Project-URL: Issues, https://github.com/nipil/harbor-ls/issues
Classifier: Programming Language :: Python :: 3
Classifier: Operating System :: OS Independent
Requires-Python: >=3.9
License-File: LICENSE
Dynamic: license-file
